shipyard_jira/__init__.py
shipyard_jira/cli/add_comment.py
shipyard_jira/cli/create_ticket.py
shipyard_jira/cli/edit_ticket.py
shipyard_jira/jira.py
shipyard_jira-0.1.3.dist-info/METADATA
shipyard_jira-0.1.3.dist-info/WHEEL
shipyard_jira-0.1.3.dist-info/RECORD
