Metadata-Version: 2.1
Name: shipyard-jira
Version: 0.1.3
Summary: A local client for connecting and working with Jira
Author: JR
Author-email: johnathan.rodriguez@shipyardapp.com
Requires-Python: >=3.9,<4.0
Classifier: Programming Language :: Python :: 3
Classifier: Programming Language :: Python :: 3.9
Classifier: Programming Language :: Python :: 3.10
Classifier: Programming Language :: Python :: 3.11
Requires-Dist: requests (>=2.30.0,<3.0.0)
Requires-Dist: shipyard-templates (>=0.1.2,<0.2.0)
